[
  {
    "id": 0,
    "first_name": "Alice",
    "last_name": "Johnson",
    "email": "alice.johnson@email.com",
    "username": "alice_j",
    "phone": "+1-555-1234",
    "field_0": "Arbitrary info 1",
    "field_1": "Arbitrary info 2",
    "field_2": "Arbitrary info 3",
    "field_3": "Arbitrary info 4"
  },
  {
    "id": 1,
    "first_name": "Bob",
    "last_name": "Smith",
    "email": "bob.smith@email.com",
    "username": "bob_smith42",
    "phone": "+1-555-5678",
    "field_0": "Random data A",
    "field_1": "Random data B",
    "field_2": "Random data C",
    "field_3": "Random data D"
  },
  {
    "id": 2,
    "first_name": "Charlie",
    "last_name": "Williams",
    "email": "charlie.williams@email.com",
    "username": "charlie_w",
    "phone": "+1-555-9876",
    "field_0": "Example 1",
    "field_1": "Example 2",
    "field_2": "Example 3",
    "field_3": "Example 4"
  },
  {
    "id": 3,
    "first_name": "David",
    "last_name": "Brown",
    "email": "david.brown@email.com",
    "username": "david_brown44",
    "phone": "+1-555-1122",
    "field_0": "Sample text A",
    "field_1": "Sample text B",
    "field_2": "Sample text C",
    "field_3": "Sample text D"
  },
  {
    "id": 4,
    "first_name": "Emma",
    "last_name": "Davis",
    "email": "emma.davis@email.com",
    "username": "emma_davis55",
    "phone": "+1-555-3344",
    "field_0": "Test info A",
    "field_1": "Test info B",
    "field_2": "Test info C",
    "field_3": "Test info D"
  },
  {
    "id": 5,
    "first_name": "Frank",
    "last_name": "Miller",
    "email": "frank.miller@email.com",
    "username": "frank_miller66",
    "phone": "+1-555-4455",
    "field_0": "Additional info A",
    "field_1": "Additional info B",
    "field_2": "Additional info C",
    "field_3": "Additional info D"
  },
  {
    "id": 6,
    "first_name": "Grace",
    "last_name": "Wilson",
    "email": "grace.wilson@email.com",
    "username": "grace_wilson77",
    "phone": "+1-555-5566",
    "field_0": "Info 1",
    "field_1": "Info 2",
    "field_2": "Info 3",
    "field_3": "Info 4"
  },
  {
    "id": 7,
    "first_name": "Henry",
    "last_name": "Moore",
    "email": "henry.moore@email.com",
    "username": "henry_moore88",
    "phone": "+1-555-6677",
    "field_0": "Detail A",
    "field_1": "Detail B",
    "field_2": "Detail C",
    "field_3": "Detail D"
  },
  {
    "id": 8,
    "first_name": "Ivy",
    "last_name": "Taylor",
    "email": "ivy.taylor@email.com",
    "username": "ivy_taylor99",
    "phone": "+1-555-7788",
    "field_0": "Specific data A",
    "field_1": "Specific data B",
    "field_2": "Specific data C",
    "field_3": "Specific data D"
  },
  {
    "id": 9,
    "first_name": "Jack",
    "last_name": "Anderson",
    "email": "jack.anderson@email.com",
    "username": "jack_anderson00",
    "phone": "+1-555-8899",
    "field_0": "Entry 1",
    "field_1": "Entry 2",
    "field_2": "Entry 3",
    "field_3": "Entry 4"
  },
  {
    "id": 10,
    "first_name": "Kathy",
    "last_name": "Thomas",
    "email": "kathy.thomas@email.com",
    "username": "kathy_thomas11",
    "phone": "+1-555-9900",
    "field_0": "Misc info A",
    "field_1": "Misc info B",
    "field_2": "Misc info C",
    "field_3": "Misc info D"
  },
  {
    "id": 11,
    "first_name": "Leo",
    "last_name": "Jackson",
    "email": "leo.jackson@email.com",
    "username": "leo_jackson22",
    "phone": "+1-555-1010",
    "field_0": "Uncategorized A",
    "field_1": "Uncategorized B",
    "field_2": "Uncategorized C",
    "field_3": "Uncategorized D"
  },
  {
    "id": 12,
    "first_name": "Mona",
    "last_name": "White",
    "email": "mona.white@email.com",
    "username": "mona_white33",
    "phone": "+1-555-2020",
    "field_0": "Placeholder 1",
    "field_1": "Placeholder 2",
    "field_2": "Placeholder 3",
    "field_3": "Placeholder 4"
  },
  {
    "id": 13,
    "first_name": "Nathan",
    "last_name": "Harris",
    "email": "nathan.harris@email.com",
    "username": "nathan_harris44",
    "phone": "+1-555-3131",
    "field_0": "Custom data 1",
    "field_1": "Custom data 2",
    "field_2": "Custom data 3",
    "field_3": "Custom data 4"
  },
  {
    "id": 14,
    "first_name": "Olivia",
    "last_name": "Martin",
    "email": "olivia.martin@email.com",
    "username": "olivia_martin55",
    "phone": "+1-555-4242",
    "field_0": "Example A",
    "field_1": "Example B",
    "field_2": "Example C",
    "field_3": "Example D"
  },
  {
    "id": 15,
    "first_name": "Paul",
    "last_name": "Green",
    "email": "paul.green@email.com",
    "username": "paul_green66",
    "phone": "+1-555-5353",
    "field_0": "Extra info A",
    "field_1": "Extra info B",
    "field_2": "Extra info C",
    "field_3": "Extra info D"
  }
]
